naviance/__init__.py
naviance-0.1.0.dist-info/LICENSE
naviance-0.1.0.dist-info/WHEEL
naviance-0.1.0.dist-info/METADATA
naviance-0.1.0.dist-info/RECORD
